memopy/__init__.py
memopy/memopy.py
memopy-0.0.1.dist-info/DESCRIPTION.rst
memopy-0.0.1.dist-info/METADATA
memopy-0.0.1.dist-info/metadata.json
memopy-0.0.1.dist-info/RECORD
memopy-0.0.1.dist-info/top_level.txt
memopy-0.0.1.dist-info/WHEEL
tests/__init__.py
tests/test_memopy.py
