Metadata-Version: 2.0
Name: memopy
Version: 0.0.1
Summary: Memoize / cache function call results
Home-page: https://github.com/tscizzle/memopy
Author: Tyler Singer-Clark
Author-email: tscizzle@gmail.com
License: MIT
Keywords: cache memoization function
Platform: UNKNOWN
Classifier: Intended Audience :: Developers
Classifier: Topic :: Scientific/Engineering
Classifier: License :: OSI Approved :: MIT License
Classifier: Programming Language :: Python :: 2
